{"required_modules":[],"required_permissions":[],"structure":[{"title":"Шапка","type":"header","size":4,"settings":{"description":"Записи к врачам - Добавление","title":["Добавление записи к врачу"]},"components":[]},{"title":"Форма","type":"form","size":4,"settings":{"object":"visits","command":"add","areas":[{"size":2,"blocks":[{"title":"","fields":["start_at","end_at","status"]},{"title":"","fields":["users_id","clients_id","services_id"]}]},{"size":2,"blocks":[{"title":"","fields":["store_id","cabinet_id"]},{"title":"","fields":["price","discount_type","discount_value"]}]}]},"components":{"buttons":[{"type":"submit","settings":{"title":"Добавление","background":"dark"}}]}}]}